LICENSE.md
README.md
loctocat/__init__.py
loctocat/_spinner.py
loctocat/auth.py
loctocat/exceptions.py
loctocat/predefined.py
loctocat-1.0.3.dist-info/LICENSE.md
loctocat-1.0.3.dist-info/WHEEL
loctocat-1.0.3.dist-info/METADATA
loctocat-1.0.3.dist-info/RECORD
