Metadata-Version: 2.1
Name: loctocat
Version: 1.0.3
Summary: Simple yet flexible OAuth 2.0 device flow authentication for Python
Home-page: https://github.com/celsiusnarhwal/loctocat
License: MIT
Keywords: oauth,oauth2,authentication,device-flow,asyncio
Author: celsius narhwal
Author-email: hello@celsiusnarhwal.dev
Requires-Python: >=3.8,<4.0
Classifier: License :: OSI Approved :: MIT License
Classifier: Programming Language :: Python :: 3
Classifier: Programming Language :: Python :: 3.8
Classifier: Programming Language :: Python :: 3.9
Classifier: Programming Language :: Python :: 3.10
Classifier: Programming Language :: Python :: 3.11
Requires-Dist: aiohttp (>=3.8.3,<4.0.0)
Requires-Dist: halo (>=0.0.31,<0.0.32)
Requires-Dist: oauthlib (>=3.2.2,<4.0.0)
Requires-Dist: requests (>=2.28.1,<3.0.0)
Requires-Dist: termcolor (>=2.1.1,<3.0.0)
Project-URL: Repository, https://github.com/celsiusnarhwal/loctocat
